opengraphio/__init__.py
opengraphio/opengraphio.py
opengraphio-1.0.5.dist-info/LICENSE
opengraphio-1.0.5.dist-info/METADATA
opengraphio-1.0.5.dist-info/WHEEL
opengraphio-1.0.5.dist-info/top_level.txt
opengraphio-1.0.5.dist-info/RECORD
