Metadata-Version: 2.1
Name: opengraphio
Version: 1.0.5
Summary: A Python client for opengraph.io, a website scraper to grab OpenGraph tags or supplement them when they don't exist.
Home-page: https://www.github.com/wbdana/opengraph-io-python
Author: Will Dana
Author-email: william.b.dana@gmail.com
License: UNKNOWN
Platform: UNKNOWN
Classifier: Programming Language :: Python :: 2.7
Classifier: Programming Language :: Python :: 3
Classifier: License :: OSI Approved :: MIT License
Classifier: Operating System :: OS Independent
Requires-Dist: requests (>=2.20.0)
